sliding_rate_limiter/__init__.py
sliding_rate_limiter/rate_limited_function.py
sliding_rate_limiter/region.py
sliding_rate_limiter/utils.py
sliding_rate_limiter/backends/__init__.py
sliding_rate_limiter/backends/base.py
sliding_rate_limiter/backends/memory.py
sliding_rate_limiter/backends/null.py
sliding_rate_limiter/backends/proxy.py
sliding_rate_limiter/backends/redis.py
sliding_rate_limiter-2.1.0.dist-info/METADATA
sliding_rate_limiter-2.1.0.dist-info/RECORD
sliding_rate_limiter-2.1.0.dist-info/WHEEL
sliding_rate_limiter-2.1.0.dist-info/top_level.txt
