Metadata-Version: 2.1
Name: sliding-rate-limiter
Version: 2.1.0
Summary: Sliding rate limiter using memory or a distributed Redis backend.
Home-page: https://github.com/kalibrr/sliding_rate_limiter
Author: Kalibrr Technology Ventures, Inc.
Author-email: hirenow@kalibrr.com
License: Apache Software License 2.0
Keywords: sliding_rate_limiter
Platform: UNKNOWN
Classifier: Development Status :: 2 - Pre-Alpha
Classifier: Intended Audience :: Developers
Classifier: License :: OSI Approved :: Apache Software License
Classifier: Natural Language :: English
Classifier: Programming Language :: Python :: 2
Classifier: Programming Language :: Python :: 2.7
Classifier: Programming Language :: Python :: 3
Classifier: Programming Language :: Python :: 3.4
Classifier: Programming Language :: Python :: 3.5
Classifier: Programming Language :: Python :: 3.6
Requires-Dist: six
